{
  "WW1 toxic compound sprayed on Georgian protesters, BBC evidence suggests": "https://www.bbc.com/news/articles/czrk7g50e1po",
  "Ukraine talks 'productive' but more work needed, Rubio says": "https://www.bbc.com/news/articles/cd9z2e3exk9o",
  "Early Honduras election results show Trump-backed man ahead": "https://www.bbc.com/news/articles/cx2dgp8mvmno",
  "UK MP Tulip Siddiq given jail sentence in Bangladesh after trial in her absence": "https://www.bbc.com/news/articles/c4g9dyd84lwo",
  "'I saw them driving over injured people' - the terrifying escape from war in Sudan": "https://www.bbc.com/news/articles/cpvdn8pmmd1o",
  "Death toll in Indonesia floods passes 500": "https://www.bbc.com/news/articles/c4g4enlp6kzo",
  "US lawmakers demand answers over Hegseth Venezuela boat strike claims": "https://www.bbc.com/news/articles/cp8zyp988zvo",
  "Pope Leo finds his voice on first foreign trip": "https://www.bbc.com/news/articles/cvgrwedyr0eo",
  "Ukrainian President Zelensky set for visit to Republic of Ireland": "https://www.bbc.com/news/articles/ckg989gnen5o",
  "More than 120,000 home cameras hacked for 'sexploitation' footage": "https://www.bbc.com/news/articles/cj01q6p7ndlo",
  "Japanese 'One Piece' singer stopped mid-show after China-Japan feud": "https://www.bbc.com/news/articles/c997n2zlegzo",
  "Husband and wife accused of using spycam and earpieces to win almost £600k at Australian casino": "https://www.bbc.com/news/articles/c075zd0j2j3o",
  "Why 2026 will be a year like no other for India's Sun mission": "https://www.bbc.com/news/articles/c8dy9qp71v2o",
  "Greek sheep and goat cull raises fears of feta cheese shortage": "https://www.bbc.com/news/articles/cgex9d0212xo",
  "Nigerian villagers 'too scared to speak' after hundreds of schoolchildren kidnapped": "https://www.bbc.com/news/articles/c4g6we59qe4o",
  "Drinking is a way of life in Ireland - can a warning label change that?": "https://www.bbc.com/news/articles/c2465lndrnno",
  "Why I spend hours painstakingly repairing banknotes": "https://www.bbc.com/news/articles/c5yq6g1gv4jo",
  "Tulip Siddiq MP given jail sentence in Bangladesh after trial in her absence": "https://www.bbc.com/news/articles/c4g9dyd84lwo",
  "Over 120,000 home cameras hacked for 'sexploitation' footage": "https://www.bbc.com/news/articles/cj01q6p7ndlo",
  "Singapore executes three men for drug offences over two days": "https://www.bbc.com/news/articles/c8dymv623q0o"
}